MANIFEST.in
README.rst
requirements.txt
setup.py
lisa/__init__.py
lisa/plugins/__init__.py
lisa/plugins/Freebox/__init__.py
lisa/plugins/Freebox/freebox.json
lisa/plugins/Freebox/lang/en/LC_MESSAGES/freebox.mo
lisa/plugins/Freebox/lang/en/LC_MESSAGES/freebox.po
lisa/plugins/Freebox/lang/fr/LC_MESSAGES/freebox.mo
lisa/plugins/Freebox/lang/fr/LC_MESSAGES/freebox.po
lisa/plugins/Freebox/modules/freebox.py
lisa/plugins/Freebox/web/__init__.py
lisa/plugins/Freebox/web/api.py
lisa/plugins/Freebox/web/models.py
lisa/plugins/Freebox/web/tests.py
lisa/plugins/Freebox/web/urls.py
lisa/plugins/Freebox/web/views.py
lisa_plugin_Freebox.egg-info/PKG-INFO
lisa_plugin_Freebox.egg-info/SOURCES.txt
lisa_plugin_Freebox.egg-info/dependency_links.txt
lisa_plugin_Freebox.egg-info/namespace_packages.txt
lisa_plugin_Freebox.egg-info/requires.txt
lisa_plugin_Freebox.egg-info/top_level.txt