Metadata-Version: 1.1
Name: lisa-plugin-Freebox
Version: 0.7.8.9
Summary: LISA home automation system - Plugin
Home-page: http://github.com/jfcjfc/LISA-PLUGINS-Freebox
Author: jfcjfc
Author-email: UNKNOWN
License: MIT
Platform: UNKNOWN
Classifier: Development Status :: 4 - Beta
Classifier: Environment :: Console
Classifier: License :: OSI Approved :: MIT License
Classifier: Operating System :: POSIX
Classifier: Programming Language :: Python :: 2
Classifier: Programming Language :: Python :: 2.7
Classifier: Topic :: Internet :: WWW/HTTP
Classifier: Topic :: Software Development :: Libraries :: Python Modules
